lib_ml/__init__.py
lib_ml/preprocessing.py
lib_ml/utils.py
lib_ml/version.py
remla25_team7_lib_ml-3.12.2.dist-info/METADATA
remla25_team7_lib_ml-3.12.2.dist-info/WHEEL
remla25_team7_lib_ml-3.12.2.dist-info/top_level.txt
remla25_team7_lib_ml-3.12.2.dist-info/RECORD
