Metadata-Version: 2.4
Name: remla25-team7-lib-ml
Version: 3.12.2
Requires-Python: >=3.8
Requires-Dist: nltk
Requires-Dist: scikit-learn
Requires-Dist: pandas
Dynamic: requires-dist
Dynamic: requires-python
